my_contacts/.DS_Store
my_contacts/__init__.py
my_contacts/app.py
my_contacts/classes.py
my_contacts/functions.py
my_contacts/data/mock-data.json
my_contacts-0.0.8.dist-info/METADATA
my_contacts-0.0.8.dist-info/WHEEL
my_contacts-0.0.8.dist-info/licenses/LICENSE
my_contacts-0.0.8.dist-info/RECORD
