Metadata-Version: 2.1
Name: my_contacts
Version: 0.0.8
Summary: A simple application to store your contacts
Project-URL: Homepage, https://github.com/MarioLisbona/CA-T1A3-terminal-app
Author-email: Mario Lisbona <mario.lisbona@gmail.com>
License: Copyright (c) 2018 The Python Packaging Authority
License-File: LICENSE
Classifier: License :: OSI Approved :: MIT License
Classifier: Operating System :: OS Independent
Classifier: Programming Language :: Python :: 3
Requires-Python: >=3.7
